[
  {
    "description": "    This feature includes registering, Modifying and Approval of Business Admin and\n    Customer Support Admin Users by System Admin",
    "keyword": "Feature",
    "name": "User Management : Administrator",
    "line": 1,
    "id": "user-management-:-administrator",
    "tags": [],
    "uri": "Administrator.feature",
    "elements": [
      {
        "id": "user-management-:-administrator;system-admin-is-able-to-initiate-modification-request-of-business-admin",
        "keyword": "Scenario",
        "line": 17,
        "name": "System Admin is able to initiate modification request of Business Admin",
        "tags": [
          {
            "name": "@test",
            "line": 14
          }
        ],
        "type": "scenario",
        "steps": [
          {
            "arguments": [],
            "keyword": "Given ",
            "line": 18,
            "name": "Login into Mobiquity Portal as System admin Checker1",
            "result": {
              "status": "passed",
              "duration": 12044000000
            }
          },
          {
            "arguments": [],
            "keyword": "When ",
            "line": 19,
            "name": "Navigate to Manage User, and search Business Admin",
            "result": {
              "status": "passed",
              "duration": 818000000
            }
          },
          {
            "arguments": [],
            "keyword": "And ",
            "line": 20,
            "name": "Search Business Admin",
            "result": {
              "status": "passed",
              "duration": 4336000000
            }
          },
          {
            "arguments": [],
            "keyword": "And ",
            "line": 21,
            "name": "System Admin is able to view details",
            "result": {
              "status": "passed",
              "duration": 4110000000
            }
          },
          {
            "arguments": [],
            "keyword": "And ",
            "line": 22,
            "name": "System Admin is able to edit details",
            "result": {
              "status": "passed",
              "duration": 5315000000
            }
          },
          {
            "arguments": [],
            "keyword": "Then ",
            "line": 23,
            "name": "Confirm the edit details",
            "result": {
              "status": "passed",
              "duration": 767000000
            }
          },
          {
            "arguments": [],
            "keyword": "And ",
            "line": 24,
            "name": "Navigate to My Activity and Apply Modified User filters",
            "result": {
              "status": "passed",
              "duration": 6853000000
            }
          },
          {
            "arguments": [],
            "keyword": "And ",
            "line": 25,
            "name": "Assert Created Business Admin Mobile Number and Write Created on time",
            "result": {
              "status": "passed",
              "duration": 4972000000
            }
          }
        ]
      },
      {
        "id": "user-management-:-administrator;system-admin-is-able-to-approve-of-modification-request-of-business-admin",
        "keyword": "Scenario",
        "line": 34,
        "name": "System Admin is able to approve of modification request of Business Admin",
        "tags": [
          {
            "name": "@test",
            "line": 32
          }
        ],
        "type": "scenario",
        "steps": [
          {
            "arguments": [],
            "keyword": "Given ",
            "line": 35,
            "name": "Login into Mobiquity Portal as System admin Maker",
            "result": {
              "status": "passed",
              "duration": 10076000000
            }
          },
          {
            "arguments": [],
            "keyword": "When ",
            "line": 36,
            "name": "Navigate to Approvals and filter by Submitted status",
            "result": {
              "status": "passed",
              "duration": 8521000000
            }
          },
          {
            "arguments": [],
            "keyword": "And ",
            "line": 37,
            "name": "User click on submitted user data",
            "result": {
              "status": "passed",
              "duration": 5715000000
            }
          },
          {
            "arguments": [],
            "keyword": "And ",
            "line": 38,
            "name": "Approve the Users",
            "result": {
              "status": "passed",
              "duration": 313000000
            }
          },
          {
            "arguments": [],
            "keyword": "Then ",
            "line": 39,
            "name": "User modified is approved",
            "result": {
              "status": "passed",
              "duration": 895000000
            }
          }
        ]
      },
      {
        "id": "user-management-:-administrator;registration-of-business-administrator-as-customer-care-admin",
        "keyword": "Scenario",
        "line": 49,
        "name": "Registration of Business Administrator as Customer care Admin",
        "tags": [
          {
            "name": "@test",
            "line": 47
          }
        ],
        "type": "scenario",
        "steps": [
          {
            "arguments": [],
            "keyword": "Given ",
            "line": 50,
            "name": "Login into Mobiquity Portal as System admin Maker",
            "result": {
              "status": "passed",
              "duration": 10184000000
            }
          },
          {
            "arguments": [],
            "keyword": "When ",
            "line": 51,
            "name": "Navigate to User Management and Click on register",
            "result": {
              "status": "passed",
              "duration": 423000000
            }
          },
          {
            "arguments": [],
            "keyword": "And ",
            "line": 52,
            "name": "Select User type as Adminstrator and click on Customer care Admin",
            "result": {
              "status": "passed",
              "duration": 5780000000
            }
          },
          {
            "arguments": [],
            "keyword": "And ",
            "line": 53,
            "name": "Enter all the details",
            "result": {
              "status": "passed",
              "duration": 8407000000
            }
          },
          {
            "arguments": [],
            "keyword": "Then ",
            "line": 54,
            "name": "Confirmation message is displayed",
            "result": {
              "status": "passed",
              "duration": 927000000
            }
          },
          {
            "arguments": [],
            "keyword": "And ",
            "line": 55,
            "name": "Navigate to My Activity and Apply Add User filters",
            "result": {
              "status": "passed",
              "duration": 4974000000
            }
          },
          {
            "arguments": [],
            "keyword": "Then ",
            "line": 56,
            "name": "Assert Created Customer care Admin Mobile Number and Write Created on time",
            "result": {
              "status": "passed",
              "duration": 5134000000
            }
          }
        ]
      },
      {
        "id": "user-management-:-administrator;approval--to-create-customer-care-admin",
        "keyword": "Scenario",
        "line": 65,
        "name": "Approval  to create Customer Care Admin",
        "tags": [
          {
            "name": "@test",
            "line": 63
          }
        ],
        "type": "scenario",
        "steps": [
          {
            "arguments": [],
            "keyword": "Given ",
            "line": 66,
            "name": "Login into Mobiquity Portal as System admin Checker1",
            "result": {
              "status": "passed",
              "duration": 9858000000
            }
          },
          {
            "arguments": [],
            "keyword": "When ",
            "line": 67,
            "name": "Navigate to Approvals and filter by Submitted status",
            "result": {
              "status": "passed",
              "duration": 7705000000
            }
          },
          {
            "arguments": [],
            "keyword": "And ",
            "line": 68,
            "name": "User click on submitted user data",
            "result": {
              "status": "passed",
              "duration": 5807000000
            }
          },
          {
            "arguments": [],
            "keyword": "And ",
            "line": 69,
            "name": "Approve the Users",
            "result": {
              "status": "passed",
              "duration": 568000000
            }
          },
          {
            "arguments": [],
            "keyword": "Then ",
            "line": 70,
            "name": "User status is approved",
            "result": {
              "status": "passed",
              "duration": 994000000
            }
          },
          {
            "arguments": [],
            "keyword": "Then ",
            "line": 71,
            "name": "Logout",
            "result": {
              "status": "passed",
              "duration": 982000000
            }
          },
          {
            "arguments": [],
            "keyword": "Given ",
            "line": 72,
            "name": "Login into Mobiquity Portal as System admin Maker",
            "result": {
              "status": "passed",
              "duration": 9816000000
            }
          },
          {
            "arguments": [],
            "keyword": "When ",
            "line": 73,
            "name": "Navigate to Manage User, and search Business Admin",
            "result": {
              "status": "passed",
              "duration": 679000000
            }
          },
          {
            "arguments": [],
            "keyword": "And ",
            "line": 74,
            "name": "Assert Created Customer Admin Mobile Number",
            "result": {
              "status": "passed",
              "duration": 5466000000
            }
          }
        ]
      },
      {
        "id": "user-management-:-administrator;system-admin-should-be-able-to-initite-modification-searching-with-all-values-(mobile,email-and-login)",
        "keyword": "Scenario",
        "line": 83,
        "name": "System admin should be able to Initite modification searching with all values (Mobile,Email and Login)",
        "tags": [
          {
            "name": "@test",
            "line": 81
          }
        ],
        "type": "scenario",
        "steps": [
          {
            "arguments": [],
            "keyword": "Given ",
            "line": 84,
            "name": "Login into Mobiquity Portal as System admin Maker",
            "result": {
              "status": "passed",
              "duration": 10196000000
            }
          },
          {
            "arguments": [],
            "keyword": "When ",
            "line": 85,
            "name": "Navigate to Manage User, and search Business Admin",
            "result": {
              "status": "passed",
              "duration": 562000000
            }
          },
          {
            "arguments": [],
            "keyword": "And ",
            "line": 86,
            "name": "Search with EmailID",
            "result": {
              "status": "passed",
              "duration": 3133000000
            }
          },
          {
            "arguments": [],
            "keyword": "And ",
            "line": 87,
            "name": "System Admin is able to view details",
            "result": {
              "status": "passed",
              "duration": 3971000000
            }
          },
          {
            "arguments": [],
            "keyword": "And ",
            "line": 88,
            "name": "System Admin is able to edit details of the user",
            "result": {
              "status": "passed",
              "duration": 4088000000
            }
          },
          {
            "arguments": [],
            "keyword": "Then ",
            "line": 89,
            "name": "Confirm the edit details Of the User",
            "result": {
              "status": "passed",
              "duration": 2735000000
            }
          },
          {
            "arguments": [],
            "keyword": "And ",
            "line": 90,
            "name": "Navigate to My Activity and Apply Modified User filters",
            "result": {
              "status": "passed",
              "duration": 4029000000
            }
          },
          {
            "arguments": [],
            "keyword": "Then ",
            "line": 91,
            "name": "Assert Created Customer care Admin Mobile Number and Write Created on time",
            "result": {
              "status": "passed",
              "duration": 4919000000
            }
          },
          {
            "arguments": [],
            "keyword": "Then ",
            "line": 92,
            "name": "Logout",
            "result": {
              "status": "passed",
              "duration": 1473000000
            }
          },
          {
            "arguments": [],
            "keyword": "Given ",
            "line": 93,
            "name": "Login into Mobiquity Portal as another System admin Checker1 after logout",
            "result": {
              "status": "passed",
              "duration": 10401000000
            }
          },
          {
            "arguments": [],
            "keyword": "When ",
            "line": 94,
            "name": "Navigate to Approvals and filter by Submitted status",
            "result": {
              "status": "passed",
              "duration": 8164000000
            }
          },
          {
            "arguments": [],
            "keyword": "And ",
            "line": 95,
            "name": "User click on submitted user data",
            "result": {
              "status": "passed",
              "duration": 6027000000
            }
          },
          {
            "arguments": [],
            "keyword": "And ",
            "line": 96,
            "name": "Approve the Users",
            "result": {
              "status": "passed",
              "duration": 665000000
            }
          },
          {
            "arguments": [],
            "keyword": "Then ",
            "line": 97,
            "name": "User modified is approved",
            "result": {
              "status": "passed",
              "duration": 818000000
            }
          }
        ]
      },
      {
        "id": "user-management-:-administrator;system-admin-should-be-able-to-initiate-deletion-of-an-existing-business-admin/customer-care-admin.",
        "keyword": "Scenario",
        "line": 108,
        "name": "System admin should be able to initiate deletion of an existing Business Admin/Customer Care Admin.",
        "tags": [
          {
            "name": "@test",
            "line": 106
          }
        ],
        "type": "scenario",
        "steps": [
          {
            "arguments": [],
            "keyword": "Given ",
            "line": 109,
            "name": "Login into Mobiquity Portal as System admin Maker",
            "result": {
              "status": "passed",
              "duration": 10494000000
            }
          },
          {
            "arguments": [],
            "keyword": "When ",
            "line": 110,
            "name": "Navigate to Manage User, and search Business Admin",
            "result": {
              "status": "passed",
              "duration": 571000000
            }
          },
          {
            "arguments": [],
            "keyword": "And ",
            "line": 111,
            "name": "Search Business or Customer care Admin",
            "result": {
              "status": "passed",
              "duration": 2950000000
            }
          },
          {
            "arguments": [],
            "keyword": "Then ",
            "line": 112,
            "name": "System Admin is able to Delete the User",
            "result": {
              "status": "passed",
              "duration": 9361000000
            }
          },
          {
            "arguments": [],
            "keyword": "And ",
            "line": 113,
            "name": "Navigate to My Activity and Apply Modified User filters",
            "result": {
              "status": "passed",
              "duration": 3782000000
            }
          },
          {
            "arguments": [],
            "keyword": "Then ",
            "line": 114,
            "name": "Assert Created Customer care Admin Mobile Number and Write Created on time",
            "result": {
              "status": "passed",
              "duration": 5061000000
            }
          }
        ]
      },
      {
        "id": "user-management-:-administrator;approve/reject-delete-initiation-of-an-existing-business-admin/customer-care-admin.",
        "keyword": "Scenario",
        "line": 125,
        "name": "Approve/Reject delete initiation of an existing Business Admin/Customer Care Admin.",
        "tags": [
          {
            "name": "@test",
            "line": 123
          }
        ],
        "type": "scenario",
        "steps": [
          {
            "arguments": [],
            "keyword": "Given ",
            "line": 126,
            "name": "Login into Mobiquity Portal as System admin Checker1",
            "result": {
              "status": "passed",
              "duration": 10216000000
            }
          },
          {
            "arguments": [],
            "keyword": "When ",
            "line": 127,
            "name": "Navigate to the Approvals",
            "result": {
              "status": "passed",
              "duration": 4652000000
            }
          },
          {
            "arguments": [],
            "keyword": "And ",
            "line": 128,
            "name": "User click on submitted user data",
            "result": {
              "status": "passed",
              "duration": 5913000000
            }
          },
          {
            "arguments": [],
            "keyword": "Then ",
            "line": 129,
            "name": "Reject the Users",
            "result": {
              "status": "passed",
              "duration": 755000000
            }
          }
        ]
      },
      {
        "id": "user-management-:-administrator;to-verify-that-system-admin-can-approve-modification-request-of-an-existing-business-admin/customer-care-admin",
        "keyword": "Scenario",
        "line": 138,
        "name": "To verify that System admin can approve modification request of an existing Business Admin/Customer Care Admin",
        "tags": [
          {
            "name": "@test",
            "line": 136
          }
        ],
        "type": "scenario",
        "steps": [
          {
            "arguments": [],
            "keyword": "Given ",
            "line": 139,
            "name": "Login into Mobiquity Portal as System admin Maker",
            "result": {
              "status": "passed",
              "duration": 10198000000
            }
          },
          {
            "arguments": [],
            "keyword": "When ",
            "line": 140,
            "name": "Navigate to Manage User, and search Business Admin",
            "result": {
              "status": "passed",
              "duration": 417000000
            }
          },
          {
            "arguments": [],
            "keyword": "And ",
            "line": 141,
            "name": "Search with Mobile Number",
            "result": {
              "status": "passed",
              "duration": 2957000000
            }
          },
          {
            "arguments": [],
            "keyword": "And ",
            "line": 142,
            "name": "System Admin is able to view details",
            "result": {
              "status": "passed",
              "duration": 3802000000
            }
          },
          {
            "arguments": [],
            "keyword": "And ",
            "line": 143,
            "name": "System Admin is able to edit details of the user",
            "result": {
              "status": "passed",
              "duration": 4125000000
            }
          },
          {
            "arguments": [],
            "keyword": "Then ",
            "line": 144,
            "name": "Confirm the edit details Of the User",
            "result": {
              "status": "passed",
              "duration": 2776000000
            }
          },
          {
            "arguments": [],
            "keyword": "And ",
            "line": 145,
            "name": "Navigate to My Activity and Apply Modified User filters",
            "result": {
              "status": "passed",
              "duration": 4052000000
            }
          },
          {
            "arguments": [],
            "keyword": "Then ",
            "line": 146,
            "name": "Assert Created Customer care Admin Mobile Number and Write Created on time",
            "result": {
              "status": "passed",
              "duration": 5082000000
            }
          },
          {
            "arguments": [],
            "keyword": "Then ",
            "line": 147,
            "name": "Logout",
            "result": {
              "status": "passed",
              "duration": 1321000000
            }
          },
          {
            "arguments": [],
            "keyword": "Given ",
            "line": 148,
            "name": "Login into Mobiquity Portal as another System admin Checker1 after logout",
            "result": {
              "status": "passed",
              "duration": 10526000000
            }
          },
          {
            "arguments": [],
            "keyword": "When ",
            "line": 149,
            "name": "Navigate to Approvals and filter by Submitted status",
            "result": {
              "status": "passed",
              "duration": 9008000000
            }
          },
          {
            "arguments": [],
            "keyword": "And ",
            "line": 150,
            "name": "User click on submitted user data",
            "result": {
              "status": "passed",
              "duration": 6184000000
            }
          },
          {
            "arguments": [],
            "keyword": "And ",
            "line": 151,
            "name": "Approve the Users",
            "result": {
              "status": "passed",
              "duration": 1399000000
            }
          },
          {
            "arguments": [],
            "keyword": "Then ",
            "line": 152,
            "name": "User modified is approved",
            "result": {
              "status": "passed",
              "duration": 1153000000
            }
          }
        ]
      },
      {
        "id": "user-management-:-administrator;to-verify-that-business-admin-is-able-to--view-self-details",
        "keyword": "Scenario",
        "line": 161,
        "name": "To verify that Business admin is able to  view Self details",
        "tags": [
          {
            "name": "@test",
            "line": 159
          }
        ],
        "type": "scenario",
        "steps": [
          {
            "arguments": [],
            "keyword": "Given ",
            "line": 162,
            "name": "Login into Mobiquity Portal as Business admin User1",
            "result": {
              "status": "passed",
              "duration": 33449000000
            }
          },
          {
            "arguments": [],
            "keyword": "When ",
            "line": 163,
            "name": "Navigate to User Management and Click on manage user",
            "result": {
              "status": "passed",
              "duration": 585000000
            }
          },
          {
            "arguments": [],
            "keyword": "And ",
            "line": 164,
            "name": "Enter Mobile number or KYC number in search",
            "result": {
              "status": "passed",
              "duration": 1525000000
            }
          },
          {
            "arguments": [],
            "keyword": "When ",
            "line": 165,
            "name": "User Click on eye button",
            "result": {
              "status": "passed",
              "duration": 893000000
            }
          },
          {
            "arguments": [],
            "keyword": "Then ",
            "line": 166,
            "name": "Verify View Details Page",
            "result": {
              "status": "passed",
              "duration": 123000000
            }
          }
        ]
      },
      {
        "id": "user-management-:-administrator;to-verify-that-the-proper-sms-notification-&-e>>mail-should-be-sent-to-users-after-addition/modification/deletion-in-system.-(if-configured)",
        "keyword": "Scenario",
        "line": 177,
        "name": "To verify that the Proper SMS Notification & E>>mail should be sent to users after addition/modification/deletion in system. (If configured)",
        "tags": [
          {
            "name": "@test",
            "line": 175
          }
        ],
        "type": "scenario",
        "steps": [
          {
            "arguments": [],
            "keyword": "Given ",
            "line": 178,
            "name": "Login into Mobiquity Portal as System admin Checker1",
            "result": {
              "status": "passed",
              "duration": 9859000000
            }
          },
          {
            "arguments": [],
            "keyword": "When ",
            "line": 179,
            "name": "Navigate to Manage User, and search Business Admin",
            "result": {
              "status": "passed",
              "duration": 559000000
            }
          },
          {
            "arguments": [],
            "keyword": "And ",
            "line": 180,
            "name": "Search Business Admin",
            "result": {
              "status": "passed",
              "duration": 3096000000
            }
          },
          {
            "arguments": [],
            "keyword": "And ",
            "line": 181,
            "name": "System Admin is able to view details",
            "result": {
              "status": "passed",
              "duration": 4098000000
            }
          },
          {
            "arguments": [],
            "keyword": "And ",
            "line": 182,
            "name": "System Admin is able to edit details",
            "result": {
              "status": "passed",
              "duration": 5485000000
            }
          },
          {
            "arguments": [],
            "keyword": "Then ",
            "line": 183,
            "name": "Confirm the edit details",
            "result": {
              "status": "passed",
              "duration": 697000000
            }
          },
          {
            "arguments": [],
            "keyword": "And ",
            "line": 184,
            "name": "Navigate to My Activity and Apply Modified User filters",
            "result": {
              "status": "passed",
              "duration": 4465000000
            }
          },
          {
            "arguments": [],
            "keyword": "And ",
            "line": 185,
            "name": "Assert Created Business Admin Mobile Number and Write Created on time",
            "result": {
              "status": "passed",
              "duration": 4848000000
            }
          },
          {
            "arguments": [],
            "keyword": "Then ",
            "line": 186,
            "name": "Logout",
            "result": {
              "status": "passed",
              "duration": 1051000000
            }
          },
          {
            "arguments": [],
            "keyword": "Given ",
            "line": 187,
            "name": "Login into Mobiquity Portal as System admin Maker after Logout",
            "result": {
              "status": "passed",
              "duration": 9132000000
            }
          },
          {
            "arguments": [],
            "keyword": "When ",
            "line": 188,
            "name": "Navigate to Approvals and filter by Submitted status",
            "result": {
              "status": "passed",
              "duration": 9349000000
            }
          },
          {
            "arguments": [],
            "keyword": "And ",
            "line": 189,
            "name": "User click on submitted user data",
            "result": {
              "status": "passed",
              "duration": 2635000000
            }
          },
          {
            "arguments": [],
            "keyword": "And ",
            "line": 190,
            "name": "Approve the Users and Check for SMS Notification sent to user",
            "result": {
              "status": "failed",
              "error_message": "AssertionError: Timed out retrying after 15000ms: Expected to find element: `button[id=\"approve-expanded-record\"]`, but never found it. Queried from element: <body>\n    at approvals.getApproveButton (http://125.16.139.20:8023/__cypress/tests?p=cypress\\integration\\BDD\\PreRequisite\\5.Users\\Administrator.feature:3271:26)\n    at Context.eval (http://125.16.139.20:8023/__cypress/tests?p=cypress\\integration\\BDD\\PreRequisite\\5.Users\\Administrator.feature:870:16)"
            },
            "embeddings": [
              {
                "mime_type": "image/png"
              }
            ]
          }
        ]
      }
    ]
  }
]