[
  {
    "keyword": "Feature",
    "name": "Authorization profile",
    "line": 1,
    "id": "authorization-profile",
    "tags": [],
    "uri": "AuthorizationProfManagement.feature",
    "elements": [
      {
        "id": "authorization-profile;to-verify-that-system-admin-should-be-able-to-view-authorization-profile-for-the-selected-category",
        "keyword": "Scenario",
        "line": 13,
        "name": "To verify that system admin should be able to View Authorization profile for the selected category",
        "tags": [],
        "type": "scenario",
        "steps": [
          {
            "arguments": [],
            "keyword": "Given ",
            "line": 14,
            "name": "Login into Mobiquity Portal as System admin Maker",
            "result": {
              "status": "passed",
              "duration": 13537000000
            }
          },
          {
            "arguments": [],
            "keyword": "When ",
            "line": 15,
            "name": "Select Authorization profile",
            "result": {
              "status": "passed",
              "duration": 3233000000
            }
          },
          {
            "arguments": [],
            "keyword": "Then ",
            "line": 16,
            "name": "View Profiles",
            "result": {
              "status": "passed",
              "duration": 8230000000
            }
          }
        ]
      },
      {
        "id": "authorization-profile;to-verify-that-system-admin-should-be-able-to-modify-an-already-created-authorization-profile",
        "keyword": "Scenario",
        "line": 26,
        "name": "To verify that system admin should be able to modify an already created authorization profile",
        "tags": [],
        "type": "scenario",
        "steps": [
          {
            "arguments": [],
            "keyword": "Given ",
            "line": 27,
            "name": "Login into Mobiquity Portal as System admin Maker",
            "result": {
              "status": "passed",
              "duration": 8723000000
            }
          },
          {
            "arguments": [],
            "keyword": "When ",
            "line": 28,
            "name": "Select Authorization profile",
            "result": {
              "status": "passed",
              "duration": 3502000000
            }
          },
          {
            "arguments": [],
            "keyword": "Then ",
            "line": 29,
            "name": "Click on Modify Icon in front of authorization profile to modify",
            "result": {
              "status": "passed",
              "duration": 10295000000
            }
          },
          {
            "arguments": [],
            "keyword": "Then ",
            "line": 30,
            "name": "Logout",
            "result": {
              "status": "passed",
              "duration": 2484000000
            }
          },
          {
            "arguments": [],
            "keyword": "Given ",
            "line": 31,
            "name": "Login into Mobiquity Portal as another System admin Checker1 after logout",
            "result": {
              "status": "passed",
              "duration": 10661000000
            }
          },
          {
            "arguments": [],
            "keyword": "Then ",
            "line": 32,
            "name": "User approval for modified Authorization profile",
            "result": {
              "status": "passed",
              "duration": 13413000000
            }
          }
        ]
      },
      {
        "id": "authorization-profile;to-verify-that-system-admin-should-be-able-to-delete-an-authorization-profile",
        "keyword": "Scenario",
        "line": 41,
        "name": "To verify that System admin should be able to delete an authorization profile",
        "tags": [],
        "type": "scenario",
        "steps": [
          {
            "arguments": [],
            "keyword": "Given ",
            "line": 42,
            "name": "Login into Mobiquity Portal as System admin Maker",
            "result": {
              "status": "passed",
              "duration": 9714000000
            }
          },
          {
            "arguments": [],
            "keyword": "When ",
            "line": 43,
            "name": "Select Authorization profile",
            "result": {
              "status": "passed",
              "duration": 3531000000
            }
          },
          {
            "arguments": [],
            "keyword": "Then ",
            "line": 44,
            "name": "Click on Modify Icon in front of authorization profile to delete",
            "result": {
              "status": "passed",
              "duration": 4097000000
            }
          }
        ]
      }
    ]
  }
]